{
    "sourceFile": "utils/logging/config.py",
    "activeCommit": 0,
    "commits": [
        {
            "activePatchIndex": 0,
            "patches": [
                {
                    "date": 1733246273557,
                    "content": "Index: \n===================================================================\n--- \n+++ \n"
                }
            ],
            "date": 1733246273557,
            "name": "Commit-0",
            "content": "# utils/logging/config.py\r\nfrom dataclasses import dataclass\r\nfrom enum import Enum\r\nimport logging\r\nfrom pathlib import Path\r\nfrom typing import Optional, Union\r\n\r\nclass LogLevel(Enum):\r\n    \"\"\"Logging levels enumeration.\"\"\"\r\n    DEBUG = logging.DEBUG\r\n    INFO = logging.INFO\r\n    WARNING = logging.WARNING\r\n    ERROR = logging.ERROR\r\n    CRITICAL = logging.CRITICAL\r\n\r\n@dataclass\r\nclass LoggerConfig:\r\n    \"\"\"Configuration for logger instances.\"\"\"\r\n    level: LogLevel = LogLevel.INFO\r\n    file_path: Optional[Path] = None\r\n    format_string: Optional[str] = None\r\n    include_timestamp: bool = True\r\n    include_level: bool = True\r\n    include_module: bool = True\r\n    json_output: bool = False\r\n    component_name: str = \"main\""
        }
    ]
}